mlte/__init__.py
mlte_python-1.0.3.dist-info/LICENSE
mlte_python-1.0.3.dist-info/METADATA
mlte_python-1.0.3.dist-info/WHEEL
mlte_python-1.0.3.dist-info/RECORD
