Metadata-Version: 2.3
Name: mlte-python
Version: 1.0.3
Summary: An infrastructure for machine learning test and evaluation.
Author: MLTE Engineers
Requires-Python: >=3.9.1,<3.12
Classifier: Development Status :: 7 - Inactive
Classifier: Programming Language :: Python :: 3
Classifier: Programming Language :: Python :: 3.10
Classifier: Programming Language :: Python :: 3.11
Requires-Dist: mlte (>=2.0.0)
